miniverse/__init__.py
miniverse/config.py
miniverse/llm_calls.py
miniverse/llm_utils.py
miniverse/logging_utils.py
miniverse/memory.py
miniverse/orchestrator.py
miniverse/perception.py
miniverse/persistence.py
miniverse/scenario.py
miniverse/schemas.py
miniverse/simulation_rules.py
miniverse/cognition/__init__.py
miniverse/cognition/cadence.py
miniverse/cognition/context.py
miniverse/cognition/executor.py
miniverse/cognition/llm.py
miniverse/cognition/planner.py
miniverse/cognition/prompts.py
miniverse/cognition/reflection.py
miniverse/cognition/renderers.py
miniverse/cognition/runtime.py
miniverse/cognition/scratchpad.py
miniverse/environment/__init__.py
miniverse/environment/graph.py
miniverse/environment/grid.py
miniverse/environment/helpers.py
miniverse/environment/schemas.py
miniverse-0.2.0.dist-info/METADATA
miniverse-0.2.0.dist-info/WHEEL
miniverse-0.2.0.dist-info/top_level.txt
miniverse-0.2.0.dist-info/RECORD
