Metadata-Version: 2.4
Name: miniverse
Version: 0.2.0
Summary: Build generative agent simulations with deterministic physics and emergent behavior
Author-email: "Kenneth F. Cavanagh" <ken@agency42.co>
License-Expression: MIT
Project-URL: Homepage, https://github.com/miniverse-ai/miniverse
Project-URL: Documentation, https://github.com/miniverse-ai/miniverse#readme
Project-URL: Repository, https://github.com/miniverse-ai/miniverse
Project-URL: Issues, https://github.com/miniverse-ai/miniverse/issues
Project-URL: Changelog, https://github.com/miniverse-ai/miniverse/blob/main/CHANGELOG.md
Keywords: llm,agents,simulation,ai,multi-agent,generative-agents,stanford
Classifier: Development Status :: 3 - Alpha
Classifier: Intended Audience :: Developers
Classifier: Intended Audience :: Science/Research
Classifier: Programming Language :: Python :: 3
Classifier: Programming Language :: Python :: 3.10
Classifier: Programming Language :: Python :: 3.11
Classifier: Programming Language :: Python :: 3.12
Classifier: Programming Language :: Python :: 3.13
Classifier: Topic :: Scientific/Engineering :: Artificial Intelligence
Classifier: Topic :: Software Development :: Libraries :: Python Modules
Requires-Python: >=3.10
Requires-Dist: pydantic>=2.0.0
Requires-Dist: python-dotenv>=1.0.0
Requires-Dist: mirascope>=1.18.0
Requires-Dist: anthropic>=0.40.0
Requires-Dist: openai>=1.0.0
Requires-Dist: asyncpg>=0.29.0
Requires-Dist: tenacity>=8.2.3
Provides-Extra: dev
Requires-Dist: pytest>=7.0.0; extra == "dev"
Requires-Dist: pytest-asyncio>=0.21.0; extra == "dev"
